CHANGES.txt
COPYRIGHT.txt
LICENSE.txt
README.txt
TODO.txt
ez_setup.py
setup.py
docs/Makefile
docs/conf.py
docs/index.rst
docs/.static/logo_hi.gif
docs/.static/repoze.css
docs/docroot/site/index.html
docs/docroot/site/business/ch.gaschart.gif
docs/docroot/site/business/index.html
docs/docroot/site/lifestyle/index.html
docs/docroot/site/lifestyle/recorate.jpg
docs/docroot/site/news/another_story.html
docs/docroot/site/news/index.html
docs/docroot/site/sports/index.html
docs/docroot/static/rules/default.xml
docs/docroot/static/rules/index.xml
docs/docroot/static/rules/story.xml
docs/docroot/static/themes/default.css
docs/docroot/static/themes/default.html
docs/docroot/static/themes/lifestyle.css
docs/docroot/static/themes/lifestyle.html
docs/docroot/static/themes/news.css
docs/docroot/static/themes/news.html
docs/docroot/static/themes/sports.css
docs/docroot/static/themes/sports.html
docs/etc/dv_news.xml
docs/etc/paste.ini
repoze/__init__.py
repoze.dvselect.egg-info/PKG-INFO
repoze.dvselect.egg-info/SOURCES.txt
repoze.dvselect.egg-info/dependency_links.txt
repoze.dvselect.egg-info/entry_points.txt
repoze.dvselect.egg-info/namespace_packages.txt
repoze.dvselect.egg-info/not-zip-safe
repoze.dvselect.egg-info/requires.txt
repoze.dvselect.egg-info/test_info.txt
repoze.dvselect.egg-info/top_level.txt
repoze/dvselect/__init__.py
repoze/dvselect/tests.py